Workbook

Sheet Customer Sheet
A1: Customer_ID | B1: Customer_Name | C1: City | D1: Segment
A2: C101 | B2: Rahul Shah | C2: Mumbai | D2: Corporate
A3: C102 | B3: Priya Patel | C3: Pune | D3: Consumer
A4: C103 | B4: Amit Kumar | C4: Delhi | D4: Corporate
A5: C104 | B5: Neha Singh | C5: Bangalore | D5: Consumer
A6: C105 | B6: Karan Mehta | C6: Hyderabad | D6: Home Office
A7: C106 | B7: Sneha Joshi | C7: Nashik | D7: Consumer
A8: C107 | B8: Vikram Desai | C8: Ahmedabad | D8: Corporate
A9: C108 | B9: Pooja Verma | C9: Chennai | D9: Consumer
A10: C109 | B10: Arjun Nair | C10: Kochi | D10: Home Office
A11: C110 | B11: Riya Kapoor | C11: Kolkata | D11: Corporate

Sheet Product sheet
A1: Product_ID | B1: Product_Name | C1: Category | D1: Cost
A2: P001 | B2: Laptop | C2: Electronics | D2: 45000
A3: P002 | B3: Smartphone | C3: Electronics | D3: 18000
A4: P003 | B4: Headphones | C4: Electronics | D4: 1500
A5: P004 | B5: Office Chair | C5: Furniture | D5: 3500
A6: P005 | B6: Study Table | C6: Furniture | D6: 6000
A7: P006 | B7: Printer | C7: Electronics | D7: 7000
A8: P007 | B8: Notebook Pack | C8: Stationery | D8: 200
A9: P008 | B9: Pen Set | C9: Stationery | D9: 100
A10: P009 | B10: Monitor | C10: Electronics | D10: 12000
A11: P010 | B11: Keyboard | C11: Electronics | D11: 800

Sheet Sheet3
A1: City | B1: Region
A2: Mumbai | B2: West
A3: Pune | B3: West
A4: Nashik | B4: West
A5: Ahmedabad | B5: West
A6: Delhi | B6: North
A7: Kolkata | B7: East
A8: Bangalore | B8: South
A9: Chennai | B9: South
A10: Hyderabad | B10: South
A11: Kochi | B11: South

Sheet Sheet9
A3: Row Labels | B3: Sum of Profit
A4: Headphones | B4: 7400
A5: Keyboard | B5: 2000
A6: Laptop | B6: 21000
A7: Monitor | B7: 13000
A8: Notebook Pack | B8: 1500
A9: Office Chair | B9: 8100
A10: Pen Set | B10: 1200
A11: Printer | B11: 2500
A12: Smartphone | B12: 78000
A13: Study Table | B13: 2500
A14: Grand Total | B14: 137200

Sheet Orders Sheet
A1: Order_ID | B1: Order_Date | C1: Customer_ID | D1: Product_ID | E1: Quantity | F1: Sales | G1: Revenue | H1: Cost | I1: Profit | J1: Profit Margin | K1: Product Name
A2: O1001 | B2: 45658 | C2: C101 | D2: P001 | E2: 1 | F2: 55000 | G2: =F2*E2 -> 55000 | H2: =_xlfn.XLOOKUP(D2,'Product sheet'!A:A,'Product sheet'!D:D) -> 45000 | I2: =(F2-H2)*E2 -> 10000 | J2: =I2/G2 -> 0.18181818 | K2: =_xlfn.XLOOKUP(D2,'Product sheet'!A:A,'Product sheet'!B:B) -> Laptop
A3: O1002 | B3: 45659 | C3: C102 | D3: P002 | E3: 2 | F3: =SUBTOTAL(109,F2) -> 55000 | G3: =F3*E3 -> 110000 | H3: =_xlfn.XLOOKUP(D3,'Product sheet'!A:A,'Product sheet'!D:D) -> 18000 | I3: =(F3-H3)*E3 -> 74000 | J3: =I3/G3 -> 0.67272727 | K3: =_xlfn.XLOOKUP(D3,'Product sheet'!A:A,'Product sheet'!B:B) -> Smartphone
A4: O1003 | B4: 45660 | C4: C103 | D4: P003 | E4: 3 | F4: 2500 | G4: =F4*E4 -> 7500 | H4: =_xlfn.XLOOKUP(D4,'Product sheet'!A:A,'Product sheet'!D:D) -> 1500 | I4: =(F4-H4)*E4 -> 3000 | J4: =I4/G4 -> 0.4 | K4: =_xlfn.XLOOKUP(D4,'Product sheet'!A:A,'Product sheet'!B:B) -> Headphones
A5: O1004 | B5: 45661 | C5: C104 | D5: P004 | E5: 2 | F5: 5000 | G5: =F5*E5 -> 10000 | H5: =_xlfn.XLOOKUP(D5,'Product sheet'!A:A,'Product sheet'!D:D) -> 3500 | I5: =(F5-H5)*E5 -> 3000 | J5: =I5/G5 -> 0.3 | K5: =_xlfn.XLOOKUP(D5,'Product sheet'!A:A,'Product sheet'!B:B) -> Office Chair
A6: O1005 | B6: 45662 | C6: C105 | D6: P005 | E6: 1 | F6: 8500 | G6: =F6*E6 -> 8500 | H6: =_xlfn.XLOOKUP(D6,'Product sheet'!A:A,'Product sheet'!D:D) -> 6000 | I6: =(F6-H6)*E6 -> 2500 | J6: =I6/G6 -> 0.29411765 | K6: =_xlfn.XLOOKUP(D6,'Product sheet'!A:A,'Product sheet'!B:B) -> Study Table
A7: O1006 | B7: 45663 | C7: C106 | D7: P006 | E7: 1 | F7: 9500 | G7: =F7*E7 -> 9500 | H7: =_xlfn.XLOOKUP(D7,'Product sheet'!A:A,'Product sheet'!D:D) -> 7000 | I7: =(F7-H7)*E7 -> 2500 | J7: =I7/G7 -> 0.26315789 | K7: =_xlfn.XLOOKUP(D7,'Product sheet'!A:A,'Product sheet'!B:B) -> Printer
A8: O1007 | B8: 45664 | C8: C107 | D8: P009 | E8: 2 | F8: 15000 | G8: =F8*E8 -> 30000 | H8: =_xlfn.XLOOKUP(D8,'Product sheet'!A:A,'Product sheet'!D:D) -> 12000 | I8: =(F8-H8)*E8 -> 6000 | J8: =I8/G8 -> 0.2 | K8: =_xlfn.XLOOKUP(D8,'Product sheet'!A:A,'Product sheet'!B:B) -> Monitor
A9: O1008 | B9: 45665 | C9: C108 | D9: P010 | E9: 5 | F9: 1200 | G9: =F9*E9 -> 6000 | H9: =_xlfn.XLOOKUP(D9,'Product sheet'!A:A,'Product sheet'!D:D) -> 800 | I9: =(F9-H9)*E9 -> 2000 | J9: =I9/G9 -> 0.33333333 | K9: =_xlfn.XLOOKUP(D9,'Product sheet'!A:A,'Product sheet'!B:B) -> Keyboard
A10: O1009 | B10: 45666 | C10: C109 | D10: P007 | E10: 10 | F10: 350 | G10: =F10*E10 -> 3500 | H10: =_xlfn.XLOOKUP(D10,'Product sheet'!A:A,'Product sheet'!D:D) -> 200 | I10: =(F10-H10)*E10 -> 1500 | J10: =I10/G10 -> 0.42857143 | K10: =_xlfn.XLOOKUP(D10,'Product sheet'!A:A,'Product sheet'!B:B) -> Notebook Pack
A11: O1010 | B11: 45667 | C11: C110 | D11: P008 | E11: 15 | F11: 180 | G11: =F11*E11 -> 2700 | H11: =_xlfn.XLOOKUP(D11,'Product sheet'!A:A,'Product sheet'!D:D) -> 100 | I11: =(F11-H11)*E11 -> 1200 | J11: =I11/G11 -> 0.44444444 | K11: =_xlfn.XLOOKUP(D11,'Product sheet'!A:A,'Product sheet'!B:B) -> Pen Set
A12: O1011 | B12: 45668 | C12: C101 | D12: P002 | E12: 1 | F12: 22000 | G12: =F12*E12 -> 22000 | H12: =_xlfn.XLOOKUP(D12,'Product sheet'!A:A,'Product sheet'!D:D) -> 18000 | I12: =(F12-H12)*E12 -> 4000 | J12: =I12/G12 -> 0.18181818 | K12: =_xlfn.XLOOKUP(D12,'Product sheet'!A:A,'Product sheet'!B:B) -> Smartphone
A13: O1012 | B13: 45669 | C13: C102 | D13: P001 | E13: 1 | F13: 56000 | G13: =F13*E13 -> 56000 | H13: =_xlfn.XLOOKUP(D13,'Product sheet'!A:A,'Product sheet'!D:D) -> 45000 | I13: =(F13-H13)*E13 -> 11000 | J13: =I13/G13 -> 0.19642857 | K13: =_xlfn.XLOOKUP(D13,'Product sheet'!A:A,'Product sheet'!B:B) -> Laptop
A14: O1013 | B14: 45670 | C14: C103 | D14: P009 | E14: 2 | F14: 15500 | G14: =F14*E14 -> 31000 | H14: =_xlfn.XLOOKUP(D14,'Product sheet'!A:A,'Product sheet'!D:D) -> 12000 | I14: =(F14-H14)*E14 -> 7000 | J14: =I14/G14 -> 0.22580645 | K14: =_xlfn.XLOOKUP(D14,'Product sheet'!A:A,'Product sheet'!B:B) -> Monitor
A15: O1014 | B15: 45671 | C15: C104 | D15: P004 | E15: 3 | F15: 5200 | G15: =F15*E15 -> 15600 | H15: =_xlfn.XLOOKUP(D15,'Product sheet'!A:A,'Product sheet'!D:D) -> 3500 | I15: =(F15-H15)*E15 -> 5100 | J15: =I15/G15 -> 0.32692308 | K15: =_xlfn.XLOOKUP(D15,'Product sheet'!A:A,'Product sheet'!B:B) -> Office Chair
A16: O1015 | B16: 45672 | C16: C105 | D16: P003 | E16: 4 | F16: 2600 | G16: =F16*E16 -> 10400 | H16: =_xlfn.XLOOKUP(D16,'Product sheet'!A:A,'Product sheet'!D:D) -> 1500 | I16: =(F16-H16)*E16 -> 4400 | J16: =I16/G16 -> 0.42307692 | K16: =_xlfn.XLOOKUP(D16,'Product sheet'!A:A,'Product sheet'!B:B) -> Headphones

Sheet Pivot Table
B1: Product Name
B2: Headphones | C2: Keyboard | D2: Laptop | E2: Monitor | F2: Notebook Pack | G2: Office Chair | H2: Pen Set | I2: Printer | J2: Smartphone | K2: Study Table | L2: Grand Total
A3: Sum of Revenue | B3: 17900 | C3: 6000 | D3: 111000 | E3: 61000 | F3: 3500 | G3: 25600 | H3: 2700 | I3: 9500 | J3: 132000 | K3: 8500 | L3: 377700
